{
  "titulo": "🚨 El error fiscal que casi le cuesta caro a este inversor no residente",
  "subtitulo": "Te cuento el caso real de Andrés: inversor NO residente fiscal en España.",
  "fecha": "2025-07-09T11:40:19.478Z",
  "url": "https://fiscalizarte.substack.com/p/el-error-fiscal-que-casi-le-cuesta",
  "audience": "only_paid",
  "post_type": "newsletter",
  "tipo_clasificado": "texto_normal",
  "metodo_extraccion_usado": "body_html",
  "body_text": "Hola,\nHoy te traigo el caso real de\nAndrés\n, un inversor argentino que tiene un piso en Madrid y que casi comete un error fiscal de esos que luego salen muy caros.\nAndrés no es residente fiscal en España.\nSu idea parecía buena:\nceder el usufructo de su piso a una sociedad española\n(gestionada por su hermano, residente aquí) para que la sociedad se encargara de alquilarlo, facturar y tributar.\n👉 A ojos de muchos, esto suena perfecto: Andrés no se encarga de nada, la sociedad cobra los alquileres y paga su 25% en el Impuesto sobre Sociedades. Fácil. Limpio. Legal.\nO eso pensaba…\n⚠️\nLa realidad fiscal le dio un susto:\nCuando analizamos la operación, le hice una pregunta clave:\n—\n¿Tienes claro que, aunque cedas el usufructo, tú sigues teniendo que tributar en España por ese inmueble?\nSe quedó en silencio. No lo sabía. Ni idea.\n✔️ Le expliqué que, como nudo propietario (es decir, sigue siendo dueño del piso, aunque no tenga el usufructo),\nHacienda le obliga a declarar la imputación de rentas inmobiliarias en el Impuesto sobre la Renta de No Residentes (IRNR).\n💡\n“Pero si no lo estoy alquilando yo, ¿por qué tengo que pagar?”\n—me dijo.\nPorque en España,\nla imputación de rentas no depende de si explotas el inmueble. Depende de si eres propietario (aunque sea solo la nuda propiedad).\n🔍\nQué implica esto en números:\nLa sociedad usufructuaria paga su\n25% sobre los ingresos del alquiler\n(IS).\nAndrés, como no residente, presenta su\nModelo 210\ncada año, y paga IRNR calculando un porcentaje sobre el valor catastral del piso (normalmente el\n1,1% o el 2%\n, según el municipio y si está revisado o no el valor catastral).\nSí, aunque no reciba ni un euro del alquiler.\n🚩\nSi no lo hubiese hecho bien…\nLe habría llegado un requerimiento de la Agencia Tributaria.\nLe habrían exigido pagar lo no declarado más intereses y posibles sanciones.\n✔️\nPor suerte, lo pillamos a tiempo.\nAhora tiene la estructura correcta:\nLa sociedad explota el inmueble legalmente.\nAndrés cumple con su obligación como no residente.\nSin sustos. Sin sorpresas.\n💼 Este es el tipo de casos que reviso cada semana.\nSi eres\nno residente y tienes inmuebles en España\n, y estás pensando en ceder usufructo, alquilar o vender...\nesto te interesa, y mucho.\nSi quieres que te ayude a tí tambíen, puedes hacer click en el siguiente enlace para terner una sesión de mentorización conmigo.\nMentoría 1:1\nUn saludo,\nFiscalizarte.\nFiscalizarte - Newsletter sobre Fiscalidad Inmobiliaria.",
  "body_length": 2449,
  "transcript_text": "",
  "transcript_length": 0,
  "transcript_source": "none",
  "combined_text": "Hola,\nHoy te traigo el caso real de\nAndrés\n, un inversor argentino que tiene un piso en Madrid y que casi comete un error fiscal de esos que luego salen muy caros.\nAndrés no es residente fiscal en España.\nSu idea parecía buena:\nceder el usufructo de su piso a una sociedad española\n(gestionada por su hermano, residente aquí) para que la sociedad se encargara de alquilarlo, facturar y tributar.\n👉 A ojos de muchos, esto suena perfecto: Andrés no se encarga de nada, la sociedad cobra los alquileres y paga su 25% en el Impuesto sobre Sociedades. Fácil. Limpio. Legal.\nO eso pensaba…\n⚠️\nLa realidad fiscal le dio un susto:\nCuando analizamos la operación, le hice una pregunta clave:\n—\n¿Tienes claro que, aunque cedas el usufructo, tú sigues teniendo que tributar en España por ese inmueble?\nSe quedó en silencio. No lo sabía. Ni idea.\n✔️ Le expliqué que, como nudo propietario (es decir, sigue siendo dueño del piso, aunque no tenga el usufructo),\nHacienda le obliga a declarar la imputación de rentas inmobiliarias en el Impuesto sobre la Renta de No Residentes (IRNR).\n💡\n“Pero si no lo estoy alquilando yo, ¿por qué tengo que pagar?”\n—me dijo.\nPorque en España,\nla imputación de rentas no depende de si explotas el inmueble. Depende de si eres propietario (aunque sea solo la nuda propiedad).\n🔍\nQué implica esto en números:\nLa sociedad usufructuaria paga su\n25% sobre los ingresos del alquiler\n(IS).\nAndrés, como no residente, presenta su\nModelo 210\ncada año, y paga IRNR calculando un porcentaje sobre el valor catastral del piso (normalmente el\n1,1% o el 2%\n, según el municipio y si está revisado o no el valor catastral).\nSí, aunque no reciba ni un euro del alquiler.\n🚩\nSi no lo hubiese hecho bien…\nLe habría llegado un requerimiento de la Agencia Tributaria.\nLe habrían exigido pagar lo no declarado más intereses y posibles sanciones.\n✔️\nPor suerte, lo pillamos a tiempo.\nAhora tiene la estructura correcta:\nLa sociedad explota el inmueble legalmente.\nAndrés cumple con su obligación como no residente.\nSin sustos. Sin sorpresas.\n💼 Este es el tipo de casos que reviso cada semana.\nSi eres\nno residente y tienes inmuebles en España\n, y estás pensando en ceder usufructo, alquilar o vender...\nesto te interesa, y mucho.\nSi quieres que te ayude a tí tambíen, puedes hacer click en el siguiente enlace para terner una sesión de mentorización conmigo.\nMentoría 1:1\nUn saludo,\nFiscalizarte.\nFiscalizarte - Newsletter sobre Fiscalidad Inmobiliaria.",
  "combined_length": 2449,
  "media_upload_ids": NaN,
  "duracion_media": NaN,
  "estado_extraccion": "OK",
  "notas": ""
}