{
  "titulo": "Lo que ningún gurú del sector te cuenta pero que deberías saber siendo un pequeño inversor inmobiliario...",
  "subtitulo": "Porqué no te suele interesar montar una SOCIEDAD PATRIMONIAL.",
  "fecha": "2025-05-05T15:06:08.404Z",
  "url": "https://fiscalizarte.substack.com/p/lo-que-ningun-guru-del-sector-te",
  "audience": "everyone",
  "post_type": "newsletter",
  "tipo_clasificado": "texto_normal",
  "metodo_extraccion_usado": "body_html",
  "body_text": "Lo que ningún gurú del sector te cuenta pero que deberías saber siendo un pequeño inversor inmobiliario.\nMe encuentro habitualmente en redes sociales a influencers defendiendo el uso de sociedades patrimoniales cómo véhiculo de inversión inmobiliaria.\nIncluso el propio José Elías… el otro día me saltó un reel suyo donde defendía el uso de este tipo de sociedades cómo vehículo personales de inversión inmobiliaria.\nQue sí… que puede tener sentido.\nPero para gente cómo él… que se mete varios kilos de euros al año.\nSin embargo… para el pequeño inversor\n(cómo tú y como yo)\n,\nNO LO TIENE.\nEl reel de José Elías… terminaba vendiendoté su servicio de planificación fiscal por 5k…\nAl pequeño inversor hay que decirle la verdad.\nNo hay que venderle humo.\nEstoy hasta los coj… de que se venda humo por redes sociales.\nYo te soy sincero.\nPara eso estás suscrito a mi newsletter.\nDíficilmente… siendo un pequeño inversor con 4-5 pisos, te pueda llegar a interesar constituir una sociedad patrimonial para canalizar tus inmuebles a través de ella.\nY esta es la puta realidad.\nY ojo que siempre existen excepciones.. pero suele ocurrir en muy pocas ocasiones.\nLo de la patrimonial queda guay en el reel de instragram… pero nada más.\n¿Y porqué no te va a interesar?\nPorque cómo pequeño inversor, debes anteponer la financiación a la fiscalidad.\nEn tus prioridades, DEBE estar en primer lugar la FINANCIACIÓN.\nY en segundo lugar, la FISCALIDAD.\nPor lo tanto, si eres un pequeño inversor asalariado que depende de su sueldo para comprar inmuebles con financiación… OLVÍDATE de una sociedad patrimonial.\nOlvídate.\nPunto.\nDEBES poner el foco en generar los máximos ingresos posibles para intentar hacer la bola  d e nieve lo más grande posible cúanto antes.\nCombinar operaciones patrimoniales con operaciones de capitalización.\nY apalancar bien los pisitos que compras para alquilar e intentar  poner el mínimo capital posible.\nPero cuidado.\nNo quiero que me\nmal-interpretes.\nNo te estoy diciendo que descuides la fiscalidad.\nSolo te digo que te dejes de pajas mentales.\nPon  los pies en la tierra.\nNo eres José Elías.\nDebes centrar tu esfuerzo en conocer cómo funciona el IRPF.\nEl 95% de los inversores NO saben declarar los alquileres de sus pisos.\nIntenta controlar todos los aspectos de este impuesto\n(IRPF)\ne intenta convertirte en un experto fiscal del mismo.\nPorque tu rendimiento depende de cómo declarás los rendimientos que te generán tus pisos en el IRPF.\nY para ayudarte ya estoy yo.\n¿Cómo?\nExplicándote TODO.\nTODO.\n¿Dónde?\nAquí\nHazte premium y entra al grupo.\nUn saludo,\nManu,\nFiscalizarte.",
  "body_length": 2590,
  "transcript_text": "",
  "transcript_length": 0,
  "transcript_source": "none",
  "combined_text": "Lo que ningún gurú del sector te cuenta pero que deberías saber siendo un pequeño inversor inmobiliario.\nMe encuentro habitualmente en redes sociales a influencers defendiendo el uso de sociedades patrimoniales cómo véhiculo de inversión inmobiliaria.\nIncluso el propio José Elías… el otro día me saltó un reel suyo donde defendía el uso de este tipo de sociedades cómo vehículo personales de inversión inmobiliaria.\nQue sí… que puede tener sentido.\nPero para gente cómo él… que se mete varios kilos de euros al año.\nSin embargo… para el pequeño inversor\n(cómo tú y como yo)\n,\nNO LO TIENE.\nEl reel de José Elías… terminaba vendiendoté su servicio de planificación fiscal por 5k…\nAl pequeño inversor hay que decirle la verdad.\nNo hay que venderle humo.\nEstoy hasta los coj… de que se venda humo por redes sociales.\nYo te soy sincero.\nPara eso estás suscrito a mi newsletter.\nDíficilmente… siendo un pequeño inversor con 4-5 pisos, te pueda llegar a interesar constituir una sociedad patrimonial para canalizar tus inmuebles a través de ella.\nY esta es la puta realidad.\nY ojo que siempre existen excepciones.. pero suele ocurrir en muy pocas ocasiones.\nLo de la patrimonial queda guay en el reel de instragram… pero nada más.\n¿Y porqué no te va a interesar?\nPorque cómo pequeño inversor, debes anteponer la financiación a la fiscalidad.\nEn tus prioridades, DEBE estar en primer lugar la FINANCIACIÓN.\nY en segundo lugar, la FISCALIDAD.\nPor lo tanto, si eres un pequeño inversor asalariado que depende de su sueldo para comprar inmuebles con financiación… OLVÍDATE de una sociedad patrimonial.\nOlvídate.\nPunto.\nDEBES poner el foco en generar los máximos ingresos posibles para intentar hacer la bola  d e nieve lo más grande posible cúanto antes.\nCombinar operaciones patrimoniales con operaciones de capitalización.\nY apalancar bien los pisitos que compras para alquilar e intentar  poner el mínimo capital posible.\nPero cuidado.\nNo quiero que me\nmal-interpretes.\nNo te estoy diciendo que descuides la fiscalidad.\nSolo te digo que te dejes de pajas mentales.\nPon  los pies en la tierra.\nNo eres José Elías.\nDebes centrar tu esfuerzo en conocer cómo funciona el IRPF.\nEl 95% de los inversores NO saben declarar los alquileres de sus pisos.\nIntenta controlar todos los aspectos de este impuesto\n(IRPF)\ne intenta convertirte en un experto fiscal del mismo.\nPorque tu rendimiento depende de cómo declarás los rendimientos que te generán tus pisos en el IRPF.\nY para ayudarte ya estoy yo.\n¿Cómo?\nExplicándote TODO.\nTODO.\n¿Dónde?\nAquí\nHazte premium y entra al grupo.\nUn saludo,\nManu,\nFiscalizarte.",
  "combined_length": 2590,
  "media_upload_ids": NaN,
  "duracion_media": NaN,
  "estado_extraccion": "OK",
  "notas": ""
}